py15rock/__init__.py
py15rock/api_config.py
py15rock/get.py
py15rock-0.0.38.dist-info/AUTHORS.rst
py15rock-0.0.38.dist-info/LICENSE
py15rock-0.0.38.dist-info/METADATA
py15rock-0.0.38.dist-info/WHEEL
py15rock-0.0.38.dist-info/top_level.txt
py15rock-0.0.38.dist-info/RECORD
