Metadata-Version: 2.1
Name: py15rock
Version: 0.0.38
Summary: 15Rock's python package
Home-page: https://github.com/pypa/sampleproject
Author: Gautam Bakshi
Author-email: Gautam.Bakshi@15Rock.com
License: UNKNOWN
Project-URL: Bug Tracker, https://github.com/pypa/sampleproject/issues
Platform: UNKNOWN
Classifier: Programming Language :: Python :: 3
Classifier: License :: OSI Approved :: MIT License
Classifier: Operating System :: OS Independent
Requires-Python: >=3.6
License-File: LICENSE
License-File: AUTHORS.rst
Requires-Dist: httpx (==0.19.0)
Requires-Dist: pandas
